README.md
README.rst
setup.py
taiga_sprint_printer/__init__.py
taiga_sprint_printer/change_colors.py
taiga_sprint_printer/configuration.py
taiga_sprint_printer/errors.py
taiga_sprint_printer/main.py
taiga_sprint_printer/messages.py
taiga_sprint_printer/print_sprint.py
taiga_sprint_printer/prompts.py
taiga_sprint_printer/utils.py
taiga_sprint_printer.egg-info/PKG-INFO
taiga_sprint_printer.egg-info/SOURCES.txt
taiga_sprint_printer.egg-info/dependency_links.txt
taiga_sprint_printer.egg-info/entry_points.txt
taiga_sprint_printer.egg-info/not-zip-safe
taiga_sprint_printer.egg-info/requires.txt
taiga_sprint_printer.egg-info/top_level.txt
taiga_sprint_printer/templates/sprinttmp.html
tests/__init__.py
tests/test_change_colors.py
tests/test_configuration.py
tests/test_messages.py
tests/test_print_sprint.py
tests/test_utils.py