Metadata-Version: 1.1
Name: taiga-sprint-printer
Version: 0.2.0
Summary: A simple tool for printing your sprint from Taiga
Home-page: https://github.com/lotrekagency/taiga-sprint-printer
Author: Lotrek
Author-email: dimmitutto@lotrek.it
License: MIT
Keywords: taiga sprint story agile planning task management
Platform: UNKNOWN
Classifier: Intended Audience :: Developers
Classifier: Programming Language :: Python
Classifier: Programming Language :: Python :: 3
